rainebow/__init__.py
rainebow/_modidx.py
rainebow/core.py
rainebow-0.0.1.dist-info/licenses/LICENSE
rainebow-0.0.1.dist-info/METADATA
rainebow-0.0.1.dist-info/WHEEL
rainebow-0.0.1.dist-info/entry_points.txt
rainebow-0.0.1.dist-info/top_level.txt
rainebow-0.0.1.dist-info/RECORD
