Metadata-Version: 2.4
Name: rainebow
Version: 0.0.1
Summary: Utility functions for cleaning and harmonising data
Home-page: https://github.com/matt-humphrey/rainebow
Author: Matt Humphrey
Author-email: mhumphrey9@hotmail.com
License: Apache Software License 2.0
Keywords: nbdev jupyter notebook python
Classifier: Development Status :: 4 - Beta
Classifier: Intended Audience :: Developers
Classifier: Natural Language :: English
Classifier: Programming Language :: Python :: 3.10
Classifier: Programming Language :: Python :: 3.11
Classifier: Programming Language :: Python :: 3.12
Classifier: License :: OSI Approved :: Apache Software License
Requires-Python: >=3.10
License-File: LICENSE
Requires-Dist: fastcore>=1.8
Requires-Dist: pandas
Requires-Dist: polars
Requires-Dist: pyreadstat
Provides-Extra: dev
Requires-Dist: ipython; extra == "dev"
Requires-Dist: nbdev; extra == "dev"
Dynamic: author
Dynamic: author-email
Dynamic: classifier
Dynamic: description
Dynamic: description-content-type
Dynamic: home-page
Dynamic: keywords
Dynamic: license
Dynamic: license-file
Dynamic: provides-extra
Dynamic: requires-dist
Dynamic: requires-python
Dynamic: summary
